{
  "title": "Who is profiting off Reddit stock threads? And the \"Marshall Plan for Moms\"",
  "audio_link": "https://www.podtrac.com/pts/redirect.mp3/pdst.fm/e/chtbl.com/track/524GE/traffic.megaphone.fm/VMP2495432514.mp3",
  "publication_date": "2021-02-02 11:00:00 UTC",
  "summary": "Kara and Scott talk about more fall out from the Reddit/Robinhood stock blitz. They also discuss escalating tensions between Facebook and Apple. Then in Friend of Pivot, we hear from Girls Who Code CEO Reshma Saujani, who is heading up a new movement to have mothers at the center of economic recovery called \"The Marshall Plan for Moms\". Women account for most of the jobs lost over the course of the pandemic.\nLearn more about your ad choices. Visit podcastchoices.com/adchoices",
  "itunes_episode": "174"
}