{
  "title": "Jack Dorsey's Bitcoin hopes, Biden picks a heavy hitter, and the Pegasus spyware scandal",
  "audio_link": "https://www.podtrac.com/pts/redirect.mp3/pdst.fm/e/chtbl.com/track/524GE/traffic.megaphone.fm/VMP9949208347.mp3?updated=1627017653",
  "publication_date": "2021-07-23 10:00:00 UTC",
  "summary": "Kara and Scott discuss Marjorie Taylor Greene's recent Twitter ban, Jack Dorsey's hopes for a bitcoin \"world peace,\" and the \"joyless\" Olympics. Kara has high hopes for Jonathan Kanter, Biden's pick for the Justice Department's anti-trust division. Things look a little more glum for privacy after the Pegasus Project revelations. And in listener mail, we get a question on every Zoomer's mind: Should I even bother planning for retirement?\nLearn more about your ad choices. Visit podcastchoices.com/adchoices",
  "itunes_episode": "220"
}