{
  "title": "Is Uber super f*cked? Let’s ask “Super Pumped” author Mike Isaac",
  "audio_link": "https://www.podtrac.com/pts/redirect.mp3/pdst.fm/e/chtbl.com/track/524GE/traffic.megaphone.fm/VMP1524299424.mp3",
  "publication_date": "2019-09-06 10:00:00 UTC",
  "summary": "Kara and Scott bring on NYTimes reporter, Mike Isaac, to talk about his new book \"Super Pumped: the Battle for Uber\". They pick his brain about all the Silicon Valley drama around the ride-share company. Scott's win is Walmart for taking action in the gun-control debate. Mike comes prepared with his own fail and calls out Twitter for the hacking of Jack Dorsey's account. Scott is predicting that weWork doesn't ever actually go public. \nLearn more about your ad choices. Visit podcastchoices.com/adchoices",
  "itunes_episode": "52"
}