{
  "title": "Truth Social Sinks, More Russia Fallout for Big Tech, and Guest Elizabeth Williamson",
  "audio_link": "https://www.podtrac.com/pts/redirect.mp3/pdst.fm/e/chtbl.com/track/524GE/traffic.megaphone.fm/VMP6731474868.mp3?updated=1646716371",
  "publication_date": "2022-03-08 11:00:00 UTC",
  "summary": "Russia’s invasion has more impacts for Big Tech, including Facebook. Elon Musk wants a union vote, and Apple may have big surprises at today’s event. Also, Trump’s Truth Social does not have the largest audience ever. Guest Elizabeth Williamson joins to talk with Kara and Scott about her new book, “Sandy Hook: An American Tragedy and The Battle for Truth.”\nYou can find Elizabeth on Twitter at @NYTLiz.\n\nSend us your Listener Mail questions by calling us at 855-51-PIVOT, or via Yappa, at nymag.com/pivot.\nLearn more about your ad choices. Visit podcastchoices.com/adchoices",
  "itunes_episode": "283"
}